authexchange/__init__.py
authexchange/__main__.py
authexchange/config.py
authexchange/server.py
authexchange/blueprints/__init__.py
authexchange/blueprints/auth/__init__.py
authexchange/blueprints/auth/controllers/__init__.py
authexchange/blueprints/auth/controllers/callback.py
authexchange/blueprints/auth/controllers/logout.py
authexchange/blueprints/auth/controllers/refresh.py
authexchange/blueprints/auth/controllers/signup_login.py
authexchange/blueprints/auth/controllers/user.py
authexchange/blueprints/ping/__init__.py
authexchange/utils/__init__.py
authexchange/utils/b64.py
authexchange/utils/state.py
authexchange-0.7.6.dist-info/entry_points.txt
authexchange-0.7.6.dist-info/LICENSE
authexchange-0.7.6.dist-info/WHEEL
authexchange-0.7.6.dist-info/METADATA
authexchange-0.7.6.dist-info/RECORD
